odoo/addons/web_field_tooltip/README.rst
odoo/addons/web_field_tooltip/__init__.py
odoo/addons/web_field_tooltip/__manifest__.py
odoo/addons/web_field_tooltip/i18n/fr.po
odoo/addons/web_field_tooltip/i18n/web_field_tooltip.pot
odoo/addons/web_field_tooltip/models/__init__.py
odoo/addons/web_field_tooltip/models/ir_http.py
odoo/addons/web_field_tooltip/models/ir_model_fields_tooltip.py
odoo/addons/web_field_tooltip/models/res_users.py
odoo/addons/web_field_tooltip/readme/CONTRIBUTORS.rst
odoo/addons/web_field_tooltip/readme/DESCRIPTION.rst
odoo/addons/web_field_tooltip/readme/ROADMAP.rst
odoo/addons/web_field_tooltip/readme/USAGE.rst
odoo/addons/web_field_tooltip/security/ir_model_access.xml
odoo/addons/web_field_tooltip/security/res_groups.xml
odoo/addons/web_field_tooltip/static/description/icon.png
odoo/addons/web_field_tooltip/static/description/index.html
odoo/addons/web_field_tooltip/static/src/css/web_field_tooltip.css
odoo/addons/web_field_tooltip/static/src/js/controller.js
odoo/addons/web_field_tooltip/static/src/js/renderer.js
odoo/addons/web_field_tooltip/static/src/js/web_field_tooltip.js
odoo/addons/web_field_tooltip/tests/__init__.py
odoo/addons/web_field_tooltip/tests/test_web_field_tooltip.py
odoo/addons/web_field_tooltip/views/ir_model_fields_tooltip.xml
odoo/addons/web_field_tooltip/views/res_users.xml
odoo/addons/web_field_tooltip/views/template.xml
odoo13_addon_web_field_tooltip-13.0.1.0.1.dev5.dist-info/METADATA
odoo13_addon_web_field_tooltip-13.0.1.0.1.dev5.dist-info/WHEEL
odoo13_addon_web_field_tooltip-13.0.1.0.1.dev5.dist-info/top_level.txt
odoo13_addon_web_field_tooltip-13.0.1.0.1.dev5.dist-info/RECORD
